setup.py
python/prometheus/__init__.py
python/prometheus/client/__init__.py
python/prometheus/client/model/__init__.py
python/prometheus/client/model/metrics_pb2.py
python/prometheus_client_model.egg-info/PKG-INFO
python/prometheus_client_model.egg-info/SOURCES.txt
python/prometheus_client_model.egg-info/dependency_links.txt
python/prometheus_client_model.egg-info/top_level.txt