Metadata-Version: 1.1
Name: prometheus-client-model
Version: 0.0.1
Summary: Data model artifacts for the Prometheus client.
Home-page: http://github.com/prometheus/client_model
Author: Matt T. Proud
Author-email: matt.proud@gmail.com
License: Apache License 2.0
Platform: Platform Independent
Classifier: Development Status :: 3 - Alpha
Classifier: Intended Audience :: Developers
Classifier: Intended Audience :: System Administrators
Classifier: License :: OSI Approved :: Apache Software License
Classifier: Operating System :: OS Independent
Classifier: Topic :: Software Development :: Testing
Classifier: Topic :: System :: Monitoring
Requires: protobuf(==2.4.1)
